8bit_CPU/8bit_CPU.srcs/sources_1/new/alu_8bit.v
//==================================================
// 8-bit ALU (Arithmetic Logic Unit)
// CO224 Lab Spec 기반 구현
//==================================================

module alu_8bit (
    input  [7:0] DATA1,    // 첫 번째 입력
    input  [7:0] DATA2,    // 두 번째 입력
    input  [2:0] SELECT,   // 연산 선택 (ALUOP)
    output reg [7:0] RESULT // 결과 출력
);

    // 내부 신호
    wire [7:0] forward_out, add_out, and_out, or_out;

    // ---------------------------
    // 개별 연산 유닛 정의
    // ---------------------------

    // FORWARD Unit (DATA2 값을 그대로 전달)
    assign #1 forward_out = DATA2;

    // ADD Unit (덧셈)
    assign #2 add_out = DATA1 + DATA2;

    // AND Unit (비트 단위 AND)
    assign #1 and_out = DATA1 & DATA2;

    // OR Unit (비트 단위 OR)
    assign #1 or_out = DATA1 | DATA2;

    // ---------------------------
    // ALU 결과 선택 (MUX 동작)
    // ---------------------------
    always @(*) begin
        case (SELECT)
            3'b000: RESULT = forward_out; // loadi, mov
            3'b001: RESULT = add_out;     // add, sub (sub는 2의 보수 처리)
            3'b010: RESULT = and_out;     // and
            3'b011: RESULT = or_out;      // or
            default: RESULT = 8'b00000000; // 나머지 값은 0 출력
        endcase
    end

endmodule

8bit_CPU/8bit_CPU.srcs/sources_1/new/tb_alu_8bit.v
`timescale 1ns/1ps

module tb_alu_8bit;

    reg [7:0] DATA1, DATA2;
    reg [2:0] SELECT;
    wire [7:0] RESULT;

    integer i; // 반복문용 변수

    // ALU 인스턴스화
    alu_8bit uut (
        .DATA1(DATA1),
        .DATA2(DATA2),
        .SELECT(SELECT),
        .RESULT(RESULT)
    );

    initial begin
        // VCD 파형 파일 생성
        $dumpfile("alu_tb.vcd");
        $dumpvars(0, tb_alu_8bit);

        // 초기값 설정
        DATA1 = 0;
        DATA2 = 1;

        // 반복문으로 DATA1=0~9, DATA2=1~10 테스트
        for (i = 0; i < 10; i = i + 1) begin
            DATA1 = i;
            DATA2 = i + 1;

            // FORWARD
            SELECT = 3'b000; #10;
            $display("FORWARD: DATA1=%d, DATA2=%d -> RESULT=%d", DATA1, DATA2, RESULT);

            // ADD
            SELECT = 3'b001; #10;
            $display("ADD    : DATA1=%d, DATA2=%d -> RESULT=%d", DATA1, DATA2, RESULT);

            // AND
            SELECT = 3'b010; #10;
            $display("AND    : DATA1=%d, DATA2=%d -> RESULT=%d", DATA1, DATA2, RESULT);

            // OR
            SELECT = 3'b011; #10;
            $display("OR     : DATA1=%d, DATA2=%d -> RESULT=%d", DATA1, DATA2, RESULT);

            $display("---------------------------------------------");
        end

        $finish;
    end

endmodule

8bit_CPU/8bit_CPU.sim/sim_1/behav/xsim/alu_tb.vcd
$date
   Wed Sep 24 16:47:43 2025
$end
$version
  2022.2
$end
$timescale
  1ps
$end
$scope module tb_alu_8bit $end
$var reg 8 ! DATA1 [7:0] $end
$var reg 8 " DATA2 [7:0] $end
$var reg 3 # SELECT [2:0] $end
$var wire 8 $ RESULT [7:0] $end
$var integer 32 % i [31:0] $end
$scope module uut $end
$var wire 8 & DATA1 [7:0] $end
$var wire 8 ' DATA2 [7:0] $end
$var wire 3 ( SELECT [2:0] $end
$var reg 8 ) RESULT [7:0] $end
$var wire 8 * forward_out [7:0] $end
$var wire 8 + add_out [7:0] $end
$var wire 8 , and_out [7:0] $end
$var wire 8 - or_out [7:0] $end
$upscope $end
$upscope $end
$enddefinitions $end
#0
$dumpvars
b0 !
b1 "
b0 #
bx $
b0 %
b0 &
b1 '
b0 (
bx )
bx *
bx +
bx ,
bx -
$end
#1000
b1 $
b1 )
b1 *
b0 ,
b1 -
#2000
b1 )
b1 +
#10000
b1 #
b1 (
b1 )
#20000
b10 #
b0 $
b10 (
b0 )
#30000
b11 #
b1 $
b11 (
b1 )
#40000
b1 !
b10 "
b0 #
b1 %
b1 &
b10 '
b0 (
b1 )
#41000
b10 $
b10 )
b10 *
b0 ,
b11 -
#42000
b10 )
b11 +
#50000
b1 #
b11 $
b1 (
b11 )
#60000
b10 #
b0 $
b10 (
b0 )
#70000
b11 #
b11 $
b11 (
b11 )
#80000
b10 !
b11 "
b0 #
b10 $
b10 %
b10 &
b11 '
b0 (
b10 )
#81000
b11 $
b11 )
b11 *
b10 ,
b11 -
#82000
b11 )
b101 +
#90000
b1 #
b101 $
b1 (
b101 )
#100000
b10 #
b10 $
b10 (
b10 )
#110000
b11 #
b11 $
b11 (
b11 )
#120000
b11 !
b100 "
b0 #
b11 %
b11 &
b100 '
b0 (
b11 )
#121000
b100 $
b100 )
b100 *
b0 ,
b111 -
#122000
b100 )
b111 +
#130000
b1 #
b111 $
b1 (
b111 )
#140000
b10 #
b0 $
b10 (
b0 )
#150000
b11 #
b111 $
b11 (
b111 )
#160000
b100 !
b101 "
b0 #
b100 $
b100 %
b100 &
b101 '
b0 (
b100 )
#161000
b101 $
b101 )
b101 *
b100 ,
b101 -
#162000
b101 )
b1001 +
#170000
b1 #
b1001 $
b1 (
b1001 )
#180000
b10 #
b100 $
b10 (
b100 )
#190000
b11 #
b101 $
b11 (
b101 )
#200000
b101 !
b110 "
b0 #
b101 %
b101 &
b110 '
b0 (
b101 )
#201000
b110 $
b110 )
b110 *
b100 ,
b111 -
#202000
b110 )
b1011 +
#210000
b1 #
b1011 $
b1 (
b1011 )
#220000
b10 #
b100 $
b10 (
b100 )
#230000
b11 #
b111 $
b11 (
b111 )
#240000
b110 !
b111 "
b0 #
b110 $
b110 %
b110 &
b111 '
b0 (
b110 )
#241000
b111 $
b111 )
b111 *
b110 ,
b111 -
#242000
b111 )
b1101 +
#250000
b1 #
b1101 $
b1 (
b1101 )
#260000
b10 #
b110 $
b10 (
b110 )
#270000
b11 #
b111 $
b11 (
b111 )
#280000
b111 !
b1000 "
b0 #
b111 %
b111 &
b1000 '
b0 (
b111 )
#281000
b1000 $
b1000 )
b1000 *
b0 ,
b1111 -
#282000
b1000 )
b1111 +
#290000
b1 #
b1111 $
b1 (
b1111 )
#300000
b10 #
b0 $
b10 (
b0 )
#310000
b11 #
b1111 $
b11 (
b1111 )
#320000
b1000 !
b1001 "
b0 #
b1000 $
b1000 %
b1000 &
b1001 '
b0 (
b1000 )
#321000
b1001 $
b1001 )
b1001 *
b1000 ,
b1001 -
#322000
b1001 )
b10001 +
#330000
b1 #
b10001 $
b1 (
b10001 )
#340000
b10 #
b1000 $
b10 (
b1000 )
#350000
b11 #
b1001 $
b11 (
b1001 )
#360000
b1001 !
b1010 "
b0 #
b1001 %
b1001 &
b1010 '
b0 (
b1001 )
#361000
b1010 $
b1010 )
b1010 *
b1000 ,
b1011 -
#362000
b1010 )
b10011 +
#370000
b1 #
b10011 $
b1 (
b10011 )
#380000
b10 #
b1000 $
b10 (
b1000 )
#390000
b11 #
b1011 $
b11 (
b1011 )
#400000
b1010 %
