reg_file/reg_file.srcs/sources_1/new/regfile_8x8.v
module regfile_8x8 (
    input  wire        clk,         // CLOCK
    input  wire        rst_n,       // RESET
    input  wire [2:0]  ra1, ra2,    // OUT1ADDRESS, OUT2ADDRESS
    output wire [7:0]  rd1, rd2,    // OUT1, OUT2
    input  wire [2:0]  wa,          // INADDRESS
    input  wire [7:0]  wd,          // IN
    input  wire        we           // WRITE ENABLE
);
    reg [7:0] R[0:7];
    integer i;

    // Write
    always @(posedge clk or negedge rst_n) begin
        if (!rst_n) begin
            for (i=0; i<8; i=i+1)
                R[i] <= 8'b0;
        end else if (we) begin
            R[wa] <= wd;
        end
    end

    // Read (with write-first)
    assign rd1 = (we && (wa == ra1)) ? wd : R[ra1];
    assign rd2 = (we && (wa == ra2)) ? wd : R[ra2];

endmodule

reg_file/reg_file.srcs/sim_1/new/tb_regfile_8x8.v
`timescale 1ns/1ps
module tb_regfile_8x8;
  reg clk, rst_n;
  reg  [2:0] ra1, ra2, wa;
  reg  [7:0] wd;
  reg        we;
  wire [7:0] rd1, rd2;

  regfile_8x8 dut(.clk(clk), .rst_n(rst_n),
                  .ra1(ra1), .ra2(ra2), .rd1(rd1), .rd2(rd2),
                  .wa(wa), .wd(wd), .we(we));

  initial clk=0; always #5 clk=~clk;

  integer error_cnt;

  task automatic apply_read(input [2:0] a1, input [2:0] a2);
    begin ra1=a1; ra2=a2; #1; end
  endtask

  task automatic write_reg(input [2:0] a, input [7:0] d);
    begin
      @(negedge clk); wa=a; wd=d; we=1'b1;
      @(posedge clk);
      @(negedge clk); we=1'b0;
    end
  endtask

  // Verilog에서는 string 대신 고정폭 벡터로 메시지 전달
  task automatic expect_eq(input [7:0] got, input [7:0] exp, input [255:0] msg);
    begin
      if (got !== exp) begin
        error_cnt = error_cnt + 1;
        $display("[%0t] ERROR: %0s  got=%02h exp=%02h", $time, msg, got, exp);
      end else begin
        $display("[%0t] PASS : %0s  = %02h", $time, msg, got);
      end
    end
  endtask

  integer i;
  initial begin
    $dumpfile("tb_regfile_8x8.vcd");
    $dumpvars(0, tb_regfile_8x8);
    error_cnt = 0;

    ra1=0; ra2=0; wa=0; wd=0; we=0;
    rst_n=0; repeat(2) @(posedge clk); rst_n=1; repeat(1) @(posedge clk);

    apply_read(3'd3,3'd7);
    expect_eq(rd1,8'h00,"after reset R3");
    expect_eq(rd2,8'h00,"after reset R7");

    write_reg(3'd3,8'hA5);
    apply_read(3'd3,3'd0);
    expect_eq(rd1,8'hA5,"R3 basic write-read");
    expect_eq(rd2,8'h00,"R0 initial");

    // RAW bypass 체크
    wa=3'd5; wd=8'h3C; we=1'b1; apply_read(3'd5,3'd5);
    expect_eq(rd1,8'h3C,"RAW rd1");
    expect_eq(rd2,8'h3C,"RAW rd2");
    @(posedge clk); we=1'b0; @(negedge clk);

    // we=0 유지
    wa=3'd5; wd=8'hEE; we=1'b0; apply_read(3'd5,3'd5);
    expect_eq(rd1,8'h3C,"WE=0 hold rd1");
    expect_eq(rd2,8'h3C,"WE=0 hold rd2");

    // 경계 주소
    write_reg(3'd0,8'h11);
    write_reg(3'd7,8'h77);
    apply_read(3'd0,3'd7);
    expect_eq(rd1,8'h11,"Boundary R0");
    expect_eq(rd2,8'h77,"Boundary R7");

    // 백투백 쓰기
    write_reg(3'd1,8'h10);
    write_reg(3'd1,8'h22);
    apply_read(3'd1,3'd1);
    expect_eq(rd1,8'h22,"Back-to-back final");
    expect_eq(rd2,8'h22,"Back-to-back final p2");

    // 패턴 로드
    for (i=0;i<8;i=i+1) write_reg(i[2:0], {5'h0, i[2:0]});
    apply_read(3'd2,3'd6);
    expect_eq(rd1,8'h02,"Pattern R2");
    expect_eq(rd2,8'h06,"Pattern R6");

    if (error_cnt==0) $display("=== ALL TESTS PASSED ===");
    else              $display("=== TEST FAILED: %0d error(s) ===", error_cnt);
    #20 $finish;
  end
endmodule

reg_file/reg_file.sim/sim_1/behav/xsim/tb_regfile_8x8.vcd
$date
   Mon Aug 11 15:02:46 2025
$end
$version
  2022.2
$end
$timescale
  1ps
$end
$scope module tb_regfile_8x8 $end
$var reg 1 ! clk $end
$var reg 1 " rst_n $end
$var reg 3 # ra1 [2:0] $end
$var reg 3 $ ra2 [2:0] $end
$var reg 3 % wa [2:0] $end
$var reg 8 & wd [7:0] $end
$var reg 1 ' we $end
$var wire 8 ( rd1 [7:0] $end
$var wire 8 ) rd2 [7:0] $end
$var integer 32 * error_cnt [31:0] $end
$var integer 32 + i [31:0] $end
$scope module dut $end
$var wire 1 , clk $end
$var wire 1 - rst_n $end
$var wire 3 . ra1 [2:0] $end
$var wire 3 / ra2 [2:0] $end
$var wire 8 ( rd1 [7:0] $end
$var wire 8 ) rd2 [7:0] $end
$var wire 3 0 wa [2:0] $end
$var wire 8 1 wd [7:0] $end
$var wire 1 2 we $end
$var integer 32 3 i [31:0] $end
$upscope $end
$scope task apply_read $end
$var reg 3 4 a1 [2:0] $end
$var reg 3 5 a2 [2:0] $end
$upscope $end
$scope task write_reg $end
$var reg 3 4 a [2:0] $end
$var reg 8 6 d [7:0] $end
$upscope $end
$scope task expect_eq $end
$var reg 8 7 got [7:0] $end
$var reg 8 6 exp [7:0] $end
$var reg 256 8 msg [255:0] $end
$upscope $end
$upscope $end
$enddefinitions $end
#0
$dumpvars
0!
0"
b0 #
b0 $
b0 %
b0 &
0'
b0 (
b0 )
b0 *
bx +
0,
0-
b0 .
b0 /
b0 0
b0 1
02
bx 3
b0 4
b0 5
b0 6
b0 7
b110100101111101001100110000000000000000000000000000000000000000000000000000000000000000000000000000000000000000000000000000 8
$end
#5000
1!
1,
#10000
0!
0,
#15000
1!
1"
1,
1-
#20000
0!
0,
#25000
1!
b11 #
b111 $
1,
b11 .
b111 /
#30000
0!
b11 %
b10100101 &
1'
b10100101 (
0,
b11 0
b10100101 1
12
#35000
1!
1,
#40000
0!
b11 #
b0 $
0'
0,
b0 /
02
#41000
b101 #
b101 $
b101 %
b111100 &
1'
b111100 (
b111100 )
b101 .
b101 /
b101 0
b111100 1
12
#45000
1!
0'
b0 (
b0 )
1,
02
#50000
0!
b101 #
b101 $
b101 %
b11101110 &
0,
b11101110 1
#51000
b10 *
#55000
1!
1,
#60000
0!
b0 %
b10001 &
1'
0,
b0 0
b10001 1
12
#65000
1!
1,
#70000
0!
0'
0,
02
#75000
1!
1,
#80000
0!
b111 %
b1110111 &
1'
0,
b111 0
b1110111 1
12
#85000
1!
1,
#90000
0!
b0 #
b111 $
0'
b10001 (
b1110111 )
0,
b0 .
b111 /
02
#95000
1!
1,
#100000
0!
b1 %
b10000 &
1'
0,
b1 0
b10000 1
12
#105000
1!
1,
#110000
0!
0'
0,
02
#115000
1!
1,
#120000
0!
b1 %
b100010 &
1'
0,
b100010 1
12
#125000
1!
1,
#130000
0!
b1 #
b1 $
0'
b100010 (
b100010 )
0,
b1 .
b1 /
02
#135000
1!
1,
#140000
0!
b0 %
b0 &
1'
0,
b0 0
b0 1
12
#145000
1!
1,
#150000
0!
0'
0,
02
#155000
1!
1,
#160000
0!
b1 %
b1 &
1'
b1 (
b1 )
0,
b1 0
b1 1
12
#165000
1!
1,
#170000
0!
0'
0,
02
#175000
1!
1,
#180000
0!
b10 %
b10 &
1'
0,
b10 0
b10 1
12
#185000
1!
1,
#190000
0!
0'
0,
02
#195000
1!
1,
#200000
0!
b11 %
b11 &
1'
0,
b11 0
b11 1
12
#205000
1!
1,
#210000
0!
0'
0,
02
#215000
1!
1,
#220000
0!
b100 %
b100 &
1'
0,
b100 0
b100 1
12
#225000
1!
1,
#230000
0!
0'
0,
02
#235000
1!
1,
#240000
0!
b101 %
b101 &
1'
0,
b101 0
b101 1
12
#245000
1!
1,
#250000
0!
0'
0,
02
#255000
1!
1,
#260000
0!
b110 %
b110 &
1'
0,
b110 0
b110 1
12
#265000
1!
1,
#270000
0!
0'
0,
02
#275000
1!
1,
#280000
0!
b111 %
b111 &
1'
0,
b111 0
b111 1
12
#285000
1!
1,
#290000
0!
b10 #
b110 $
0'
b10 (
b110 )
b1000 +
0,
b10 .
b110 /
02
